{
    "counters": {
        "top": {
            "Zaahen": {
                "Name": "Zaahen",
                "win_rate": "50.39",
                "popularity": "7.19",
                "games": "4,818",
                "win_rate_diff": 0.39
            },
            "Malphite": {
                "Name": "Malphite",
                "win_rate": "44.53",
                "popularity": "3.94",
                "games": "2,641",
                "win_rate_diff": -5.47
            },
            "Aatrox": {
                "Name": "Aatrox",
                "win_rate": "53.98",
                "popularity": "3.82",
                "games": "2,562",
                "win_rate_diff": 3.98
            },
            "Darius": {
                "Name": "Darius",
                "win_rate": "52.73",
                "popularity": "3.42",
                "games": "2,293",
                "win_rate_diff": 2.73
            },
            "Ambessa": {
                "Name": "Ambessa",
                "win_rate": "51.45",
                "popularity": "3.20",
                "games": "2,144",
                "win_rate_diff": 1.45
            },
            "Garen": {
                "Name": "Garen",
                "win_rate": "49.11",
                "popularity": "3.12",
                "games": "2,089",
                "win_rate_diff": -0.89
            },
            "Jax": {
                "Name": "Jax",
                "win_rate": "47.97",
                "popularity": "2.97",
                "games": "1,991",
                "win_rate_diff": -2.03
            },
            "Sett": {
                "Name": "Sett",
                "win_rate": "49.92",
                "popularity": "2.68",
                "games": "1,793",
                "win_rate_diff": -0.08
            },
            "Renekton": {
                "Name": "Renekton",
                "win_rate": "50.91",
                "popularity": "2.61",
                "games": "1,752",
                "win_rate_diff": 0.91
            },
            "Riven": {
                "Name": "Riven",
                "win_rate": "47.45",
                "popularity": "2.45",
                "games": "1,644",
                "win_rate_diff": -2.55
            },
            "Sion": {
                "Name": "Sion",
                "win_rate": "53.66",
                "popularity": "2.34",
                "games": "1,571",
                "win_rate_diff": 3.66
            },
            "Dr. Mundo": {
                "Name": "Dr. Mundo",
                "win_rate": "54.53",
                "popularity": "2.34",
                "games": "1,566",
                "win_rate_diff": 4.53
            },
            "Mordekaiser": {
                "Name": "Mordekaiser",
                "win_rate": "55.29",
                "popularity": "2.26",
                "games": "1,512",
                "win_rate_diff": 5.29
            },
            "Fiora": {
                "Name": "Fiora",
                "win_rate": "52.29",
                "popularity": "2.22",
                "games": "1,486",
                "win_rate_diff": 2.29
            },
            "Jayce": {
                "Name": "Jayce",
                "win_rate": "51.40",
                "popularity": "2.19",
                "games": "1,469",
                "win_rate_diff": 1.4
            },
            "Yone": {
                "Name": "Yone",
                "win_rate": "51.02",
                "popularity": "2.11",
                "games": "1,417",
                "win_rate_diff": 1.02
            },
            "Kayle": {
                "Name": "Kayle",
                "win_rate": "49.32",
                "popularity": "1.96",
                "games": "1,316",
                "win_rate_diff": -0.68
            },
            "K'Sante": {
                "Name": "K'Sante",
                "win_rate": "54.24",
                "popularity": "1.95",
                "games": "1,309",
                "win_rate_diff": 4.24
            },
            "Gwen": {
                "Name": "Gwen",
                "win_rate": "53.08",
                "popularity": "1.86",
                "games": "1,249",
                "win_rate_diff": 3.08
            },
            "Irelia": {
                "Name": "Irelia",
                "win_rate": "51.69",
                "popularity": "1.86",
                "games": "1,246",
                "win_rate_diff": 1.69
            },
            "Gangplank": {
                "Name": "Gangplank",
                "win_rate": "55.70",
                "popularity": "1.78",
                "games": "1,194",
                "win_rate_diff": 5.7
            },
            "Ornn": {
                "Name": "Ornn",
                "win_rate": "52.55",
                "popularity": "1.72",
                "games": "1,155",
                "win_rate_diff": 2.55
            },
            "Shen": {
                "Name": "Shen",
                "win_rate": "48.59",
                "popularity": "1.64",
                "games": "1,097",
                "win_rate_diff": -1.41
            },
            "Camille": {
                "Name": "Camille",
                "win_rate": "48.39",
                "popularity": "1.63",
                "games": "1,089",
                "win_rate_diff": -1.61
            },
            "Gnar": {
                "Name": "Gnar",
                "win_rate": "50.87",
                "popularity": "1.55",
                "games": "1,040",
                "win_rate_diff": 0.87
            },
            "Cho'Gath": {
                "Name": "Cho'Gath",
                "win_rate": "49.42",
                "popularity": "1.55",
                "games": "1,040",
                "win_rate_diff": -0.58
            },
            "Yasuo": {
                "Name": "Yasuo",
                "win_rate": "53.59",
                "popularity": "1.52",
                "games": "1,017",
                "win_rate_diff": 3.59
            },
            "Urgot": {
                "Name": "Urgot",
                "win_rate": "47.99",
                "popularity": "1.48",
                "games": "994",
                "win_rate_diff": -2.01
            },
            "Teemo": {
                "Name": "Teemo",
                "win_rate": "48.48",
                "popularity": "1.33",
                "games": "889",
                "win_rate_diff": -1.52
            },
            "Singed": {
                "Name": "Singed",
                "win_rate": "48.74",
                "popularity": "1.31",
                "games": "876",
                "win_rate_diff": -1.26
            },
            "Nasus": {
                "Name": "Nasus",
                "win_rate": "53.49",
                "popularity": "1.28",
                "games": "860",
                "win_rate_diff": 3.49
            },
            "Gragas": {
                "Name": "Gragas",
                "win_rate": "53.08",
                "popularity": "1.28",
                "games": "859",
                "win_rate_diff": 3.08
            },
            "Yorick": {
                "Name": "Yorick",
                "win_rate": "52.25",
                "popularity": "1.26",
                "games": "846",
                "win_rate_diff": 2.25
            },
            "Vladimir": {
                "Name": "Vladimir",
                "win_rate": "52.05",
                "popularity": "1.24",
                "games": "828",
                "win_rate_diff": 2.05
            },
            "Rumble": {
                "Name": "Rumble",
                "win_rate": "50.95",
                "popularity": "1.17",
                "games": "787",
                "win_rate_diff": 0.95
            },
            "Tryndamere": {
                "Name": "Tryndamere",
                "win_rate": "52.88",
                "popularity": "1.17",
                "games": "781",
                "win_rate_diff": 2.88
            },
            "Volibear": {
                "Name": "Volibear",
                "win_rate": "54.91",
                "popularity": "1.14",
                "games": "763",
                "win_rate_diff": 4.91
            },
            "Pantheon": {
                "Name": "Pantheon",
                "win_rate": "51.69",
                "popularity": "0.97",
                "games": "652",
                "win_rate_diff": 1.69
            },
            "Kennen": {
                "Name": "Kennen",
                "win_rate": "49.14",
                "popularity": "0.96",
                "games": "643",
                "win_rate_diff": -0.86
            },
            "Olaf": {
                "Name": "Olaf",
                "win_rate": "52.43",
                "popularity": "0.95",
                "games": "637",
                "win_rate_diff": 2.43
            },
            "Illaoi": {
                "Name": "Illaoi",
                "win_rate": "51.50",
                "popularity": "0.90",
                "games": "602",
                "win_rate_diff": 1.5
            },
            "Vayne": {
                "Name": "Vayne",
                "win_rate": "51.43",
                "popularity": "0.89",
                "games": "595",
                "win_rate_diff": 1.43
            },
            "Kled": {
                "Name": "Kled",
                "win_rate": "53.91",
                "popularity": "0.88",
                "games": "588",
                "win_rate_diff": 3.91
            },
            "Akali": {
                "Name": "Akali",
                "win_rate": "52.32",
                "popularity": "0.84",
                "games": "560",
                "win_rate_diff": 2.32
            },
            "Quinn": {
                "Name": "Quinn",
                "win_rate": "49.54",
                "popularity": "0.82",
                "games": "547",
                "win_rate_diff": -0.46
            },
            "Warwick": {
                "Name": "Warwick",
                "win_rate": "48.40",
                "popularity": "0.65",
                "games": "438",
                "win_rate_diff": -1.6
            },
            "Swain": {
                "Name": "Swain",
                "win_rate": "51.72",
                "popularity": "0.61",
                "games": "406",
                "win_rate_diff": 1.72
            }
        },
        "jungle": {
            "Sylas": {
                "Name": "Sylas",
                "win_rate": "52.81",
                "popularity": "6.14",
                "games": "4,113",
                "win_rate_diff": 2.81
            },
            "Viego": {
                "Name": "Viego",
                "win_rate": "53.68",
                "popularity": "6.12",
                "games": "4,098",
                "win_rate_diff": 3.68
            },
            "Lee Sin": {
                "Name": "Lee Sin",
                "win_rate": "50.97",
                "popularity": "4.37",
                "games": "2,929",
                "win_rate_diff": 0.97
            },
            "Aatrox": {
                "Name": "Aatrox",
                "win_rate": "53.70",
                "popularity": "3.65",
                "games": "2,447",
                "win_rate_diff": 3.7
            },
            "Diana": {
                "Name": "Diana",
                "win_rate": "49.84",
                "popularity": "3.24",
                "games": "2,173",
                "win_rate_diff": -0.16
            },
            "Jarvan IV": {
                "Name": "Jarvan IV",
                "win_rate": "50.67",
                "popularity": "3.22",
                "games": "2,159",
                "win_rate_diff": 0.67
            },
            "Kha'Zix": {
                "Name": "Kha'Zix",
                "win_rate": "50.30",
                "popularity": "2.99",
                "games": "2,004",
                "win_rate_diff": 0.3
            },
            "Rengar": {
                "Name": "Rengar",
                "win_rate": "53.14",
                "popularity": "2.85",
                "games": "1,908",
                "win_rate_diff": 3.14
            },
            "Kayn": {
                "Name": "Kayn",
                "win_rate": "51.69",
                "popularity": "2.79",
                "games": "1,867",
                "win_rate_diff": 1.69
            },
            "Graves": {
                "Name": "Graves",
                "win_rate": "52.28",
                "popularity": "2.71",
                "games": "1,817",
                "win_rate_diff": 2.28
            },
            "Qiyana": {
                "Name": "Qiyana",
                "win_rate": "53.39",
                "popularity": "2.62",
                "games": "1,753",
                "win_rate_diff": 3.39
            },
            "Talon": {
                "Name": "Talon",
                "win_rate": "50.46",
                "popularity": "2.43",
                "games": "1,631",
                "win_rate_diff": 0.46
            },
            "Master Yi": {
                "Name": "Master Yi",
                "win_rate": "48.77",
                "popularity": "2.36",
                "games": "1,581",
                "win_rate_diff": -1.23
            },
            "Ekko": {
                "Name": "Ekko",
                "win_rate": "49.10",
                "popularity": "2.33",
                "games": "1,564",
                "win_rate_diff": -0.9
            },
            "Malphite": {
                "Name": "Malphite",
                "win_rate": "53.09",
                "popularity": "2.29",
                "games": "1,535",
                "win_rate_diff": 3.09
            },
            "Jax": {
                "Name": "Jax",
                "win_rate": "50.89",
                "popularity": "2.10",
                "games": "1,409",
                "win_rate_diff": 0.89
            },
            "Zed": {
                "Name": "Zed",
                "win_rate": "51.68",
                "popularity": "2.00",
                "games": "1,337",
                "win_rate_diff": 1.68
            },
            "Briar": {
                "Name": "Briar",
                "win_rate": "48.50",
                "popularity": "1.99",
                "games": "1,336",
                "win_rate_diff": -1.5
            },
            "Dr. Mundo": {
                "Name": "Dr. Mundo",
                "win_rate": "50.88",
                "popularity": "1.78",
                "games": "1,193",
                "win_rate_diff": 0.88
            },
            "Shaco": {
                "Name": "Shaco",
                "win_rate": "51.80",
                "popularity": "1.78",
                "games": "1,193",
                "win_rate_diff": 1.8
            },
            "Nidalee": {
                "Name": "Nidalee",
                "win_rate": "52.47",
                "popularity": "1.78",
                "games": "1,193",
                "win_rate_diff": 2.47
            },
            "Hecarim": {
                "Name": "Hecarim",
                "win_rate": "47.43",
                "popularity": "1.77",
                "games": "1,185",
                "win_rate_diff": -2.57
            },
            "Xin Zhao": {
                "Name": "Xin Zhao",
                "win_rate": "48.81",
                "popularity": "1.75",
                "games": "1,172",
                "win_rate_diff": -1.19
            },
            "Nocturne": {
                "Name": "Nocturne",
                "win_rate": "51.74",
                "popularity": "1.67",
                "games": "1,119",
                "win_rate_diff": 1.74
            },
            "Zaahen": {
                "Name": "Zaahen",
                "win_rate": "53.36",
                "popularity": "1.62",
                "games": "1,087",
                "win_rate_diff": 3.36
            },
            "Lillia": {
                "Name": "Lillia",
                "win_rate": "51.45",
                "popularity": "1.55",
                "games": "1,036",
                "win_rate_diff": 1.45
            },
            "Kindred": {
                "Name": "Kindred",
                "win_rate": "47.08",
                "popularity": "1.46",
                "games": "977",
                "win_rate_diff": -2.92
            },
            "Wukong": {
                "Name": "Wukong",
                "win_rate": "52.04",
                "popularity": "1.39",
                "games": "932",
                "win_rate_diff": 2.04
            },
            "Jayce": {
                "Name": "Jayce",
                "win_rate": "54.04",
                "popularity": "1.35",
                "games": "903",
                "win_rate_diff": 4.04
            },
            "Elise": {
                "Name": "Elise",
                "win_rate": "46.75",
                "popularity": "1.33",
                "games": "892",
                "win_rate_diff": -3.25
            },
            "Ambessa": {
                "Name": "Ambessa",
                "win_rate": "56.55",
                "popularity": "1.32",
                "games": "886",
                "win_rate_diff": 6.55
            },
            "Warwick": {
                "Name": "Warwick",
                "win_rate": "49.53",
                "popularity": "1.27",
                "games": "848",
                "win_rate_diff": -0.47
            },
            "Zac": {
                "Name": "Zac",
                "win_rate": "50.83",
                "popularity": "1.26",
                "games": "844",
                "win_rate_diff": 0.83
            },
            "Evelynn": {
                "Name": "Evelynn",
                "win_rate": "50.64",
                "popularity": "1.16",
                "games": "780",
                "win_rate_diff": 0.64
            },
            "Vi": {
                "Name": "Vi",
                "win_rate": "50.06",
                "popularity": "1.15",
                "games": "773",
                "win_rate_diff": 0.06
            },
            "Fiddlesticks": {
                "Name": "Fiddlesticks",
                "win_rate": "50.00",
                "popularity": "1.12",
                "games": "748",
                "win_rate_diff": 0.0
            },
            "Amumu": {
                "Name": "Amumu",
                "win_rate": "46.58",
                "popularity": "1.11",
                "games": "745",
                "win_rate_diff": -3.42
            },
            "Naafiri": {
                "Name": "Naafiri",
                "win_rate": "51.96",
                "popularity": "1.10",
                "games": "739",
                "win_rate_diff": 1.96
            },
            "Rek'Sai": {
                "Name": "Rek'Sai",
                "win_rate": "44.55",
                "popularity": "1.08",
                "games": "725",
                "win_rate_diff": -5.45
            },
            "Nunu & Willump": {
                "Name": "Nunu & Willump",
                "win_rate": "48.97",
                "popularity": "1.08",
                "games": "725",
                "win_rate_diff": -1.03
            },
            "Udyr": {
                "Name": "Udyr",
                "win_rate": "51.40",
                "popularity": "1.01",
                "games": "677",
                "win_rate_diff": 1.4
            },
            "Volibear": {
                "Name": "Volibear",
                "win_rate": "48.74",
                "popularity": "0.95",
                "games": "636",
                "win_rate_diff": -1.26
            },
            "Rammus": {
                "Name": "Rammus",
                "win_rate": "46.74",
                "popularity": "0.82",
                "games": "552",
                "win_rate_diff": -3.26
            },
            "Ivern": {
                "Name": "Ivern",
                "win_rate": "46.41",
                "popularity": "0.75",
                "games": "502",
                "win_rate_diff": -3.59
            },
            "Cho'Gath": {
                "Name": "Cho'Gath",
                "win_rate": "51.99",
                "popularity": "0.75",
                "games": "502",
                "win_rate_diff": 1.99
            },
            "Karthus": {
                "Name": "Karthus",
                "win_rate": "52.14",
                "popularity": "0.73",
                "games": "491",
                "win_rate_diff": 2.14
            },
            "Sejuani": {
                "Name": "Sejuani",
                "win_rate": "52.66",
                "popularity": "0.73",
                "games": "488",
                "win_rate_diff": 2.66
            }
        },
        "middle": {
            "Ahri": {
                "Name": "Ahri",
                "win_rate": "47.94",
                "popularity": "4.49",
                "games": "3,008",
                "win_rate_diff": -2.06
            },
            "Syndra": {
                "Name": "Syndra",
                "win_rate": "49.97",
                "popularity": "4.39",
                "games": "2,944",
                "win_rate_diff": -0.03
            },
            "Viktor": {
                "Name": "Viktor",
                "win_rate": "52.58",
                "popularity": "3.94",
                "games": "2,638",
                "win_rate_diff": 2.58
            },
            "Katarina": {
                "Name": "Katarina",
                "win_rate": "48.63",
                "popularity": "3.77",
                "games": "2,527",
                "win_rate_diff": -1.37
            },
            "Mel": {
                "Name": "Mel",
                "win_rate": "57.69",
                "popularity": "3.67",
                "games": "2,458",
                "win_rate_diff": 7.69
            },
            "Orianna": {
                "Name": "Orianna",
                "win_rate": "51.92",
                "popularity": "3.61",
                "games": "2,421",
                "win_rate_diff": 1.92
            },
            "Yasuo": {
                "Name": "Yasuo",
                "win_rate": "53.96",
                "popularity": "3.49",
                "games": "2,337",
                "win_rate_diff": 3.96
            },
            "Sylas": {
                "Name": "Sylas",
                "win_rate": "51.99",
                "popularity": "3.41",
                "games": "2,283",
                "win_rate_diff": 1.99
            },
            "Akali": {
                "Name": "Akali",
                "win_rate": "52.57",
                "popularity": "3.11",
                "games": "2,081",
                "win_rate_diff": 2.57
            },
            "Malzahar": {
                "Name": "Malzahar",
                "win_rate": "49.32",
                "popularity": "2.96",
                "games": "1,981",
                "win_rate_diff": -0.68
            },
            "Zed": {
                "Name": "Zed",
                "win_rate": "49.22",
                "popularity": "2.85",
                "games": "1,912",
                "win_rate_diff": -0.78
            },
            "LeBlanc": {
                "Name": "LeBlanc",
                "win_rate": "52.53",
                "popularity": "2.27",
                "games": "1,523",
                "win_rate_diff": 2.53
            },
            "Yone": {
                "Name": "Yone",
                "win_rate": "54.18",
                "popularity": "2.25",
                "games": "1,508",
                "win_rate_diff": 4.18
            },
            "Zoe": {
                "Name": "Zoe",
                "win_rate": "50.07",
                "popularity": "2.10",
                "games": "1,408",
                "win_rate_diff": 0.07
            },
            "Fizz": {
                "Name": "Fizz",
                "win_rate": "50.07",
                "popularity": "2.06",
                "games": "1,380",
                "win_rate_diff": 0.07
            },
            "Xerath": {
                "Name": "Xerath",
                "win_rate": "50.71",
                "popularity": "1.99",
                "games": "1,335",
                "win_rate_diff": 0.71
            },
            "Hwei": {
                "Name": "Hwei",
                "win_rate": "52.80",
                "popularity": "1.97",
                "games": "1,322",
                "win_rate_diff": 2.8
            },
            "Diana": {
                "Name": "Diana",
                "win_rate": "47.62",
                "popularity": "1.85",
                "games": "1,241",
                "win_rate_diff": -2.38
            },
            "Twisted Fate": {
                "Name": "Twisted Fate",
                "win_rate": "49.43",
                "popularity": "1.83",
                "games": "1,228",
                "win_rate_diff": -0.57
            },
            "Ryze": {
                "Name": "Ryze",
                "win_rate": "53.04",
                "popularity": "1.82",
                "games": "1,218",
                "win_rate_diff": 3.04
            },
            "Vladimir": {
                "Name": "Vladimir",
                "win_rate": "49.29",
                "popularity": "1.77",
                "games": "1,189",
                "win_rate_diff": -0.71
            },
            "Ekko": {
                "Name": "Ekko",
                "win_rate": "50.21",
                "popularity": "1.74",
                "games": "1,163",
                "win_rate_diff": 0.21
            },
            "Veigar": {
                "Name": "Veigar",
                "win_rate": "50.57",
                "popularity": "1.70",
                "games": "1,139",
                "win_rate_diff": 0.57
            },
            "Kassadin": {
                "Name": "Kassadin",
                "win_rate": "49.03",
                "popularity": "1.69",
                "games": "1,130",
                "win_rate_diff": -0.97
            },
            "Akshan": {
                "Name": "Akshan",
                "win_rate": "48.67",
                "popularity": "1.68",
                "games": "1,126",
                "win_rate_diff": -1.33
            },
            "Galio": {
                "Name": "Galio",
                "win_rate": "53.14",
                "popularity": "1.66",
                "games": "1,114",
                "win_rate_diff": 3.14
            },
            "Lux": {
                "Name": "Lux",
                "win_rate": "54.88",
                "popularity": "1.57",
                "games": "1,055",
                "win_rate_diff": 4.88
            },
            "Taliyah": {
                "Name": "Taliyah",
                "win_rate": "50.14",
                "popularity": "1.57",
                "games": "1,051",
                "win_rate_diff": 0.14
            },
            "Anivia": {
                "Name": "Anivia",
                "win_rate": "49.18",
                "popularity": "1.55",
                "games": "1,041",
                "win_rate_diff": -0.82
            },
            "Aurora": {
                "Name": "Aurora",
                "win_rate": "51.21",
                "popularity": "1.42",
                "games": "949",
                "win_rate_diff": 1.21
            },
            "Azir": {
                "Name": "Azir",
                "win_rate": "59.23",
                "popularity": "1.35",
                "games": "905",
                "win_rate_diff": 9.23
            },
            "Qiyana": {
                "Name": "Qiyana",
                "win_rate": "50.62",
                "popularity": "1.33",
                "games": "893",
                "win_rate_diff": 0.62
            },
            "Lissandra": {
                "Name": "Lissandra",
                "win_rate": "49.83",
                "popularity": "1.28",
                "games": "859",
                "win_rate_diff": -0.17
            },
            "Aurelion Sol": {
                "Name": "Aurelion Sol",
                "win_rate": "52.31",
                "popularity": "1.16",
                "games": "780",
                "win_rate_diff": 2.31
            },
            "Vex": {
                "Name": "Vex",
                "win_rate": "49.87",
                "popularity": "1.11",
                "games": "746",
                "win_rate_diff": -0.13
            },
            "Irelia": {
                "Name": "Irelia",
                "win_rate": "55.19",
                "popularity": "1.08",
                "games": "723",
                "win_rate_diff": 5.19
            },
            "Naafiri": {
                "Name": "Naafiri",
                "win_rate": "49.93",
                "popularity": "1.05",
                "games": "703",
                "win_rate_diff": -0.07
            },
            "Kayle": {
                "Name": "Kayle",
                "win_rate": "54.09",
                "popularity": "1.02",
                "games": "684",
                "win_rate_diff": 4.09
            },
            "Talon": {
                "Name": "Talon",
                "win_rate": "50.83",
                "popularity": "0.99",
                "games": "665",
                "win_rate_diff": 0.83
            },
            "Morgana": {
                "Name": "Morgana",
                "win_rate": "51.09",
                "popularity": "0.96",
                "games": "640",
                "win_rate_diff": 1.09
            },
            "Cassiopeia": {
                "Name": "Cassiopeia",
                "win_rate": "51.22",
                "popularity": "0.92",
                "games": "615",
                "win_rate_diff": 1.22
            },
            "Swain": {
                "Name": "Swain",
                "win_rate": "48.28",
                "popularity": "0.83",
                "games": "553",
                "win_rate_diff": -1.72
            },
            "Smolder": {
                "Name": "Smolder",
                "win_rate": "57.45",
                "popularity": "0.76",
                "games": "510",
                "win_rate_diff": 7.45
            },
            "Vel'Koz": {
                "Name": "Vel'Koz",
                "win_rate": "49.61",
                "popularity": "0.76",
                "games": "508",
                "win_rate_diff": -0.39
            },
            "Annie": {
                "Name": "Annie",
                "win_rate": "48.84",
                "popularity": "0.64",
                "games": "432",
                "win_rate_diff": -1.16
            },
            "Jayce": {
                "Name": "Jayce",
                "win_rate": "55.38",
                "popularity": "0.58",
                "games": "390",
                "win_rate_diff": 5.38
            },
            "Ziggs": {
                "Name": "Ziggs",
                "win_rate": "51.53",
                "popularity": "0.49",
                "games": "326",
                "win_rate_diff": 1.53
            }
        },
        "bottom": {
            "Kai'Sa": {
                "Name": "Kai'Sa",
                "win_rate": "51.88",
                "popularity": "9.80",
                "games": "6,567",
                "win_rate_diff": 1.88
            },
            "Miss Fortune": {
                "Name": "Miss Fortune",
                "win_rate": "49.70",
                "popularity": "9.63",
                "games": "6,451",
                "win_rate_diff": -0.3
            },
            "Jhin": {
                "Name": "Jhin",
                "win_rate": "52.62",
                "popularity": "7.64",
                "games": "5,116",
                "win_rate_diff": 2.62
            },
            "Caitlyn": {
                "Name": "Caitlyn",
                "win_rate": "52.53",
                "popularity": "5.80",
                "games": "3,889",
                "win_rate_diff": 2.53
            },
            "Ezreal": {
                "Name": "Ezreal",
                "win_rate": "54.49",
                "popularity": "5.71",
                "games": "3,828",
                "win_rate_diff": 4.49
            },
            "Jinx": {
                "Name": "Jinx",
                "win_rate": "49.23",
                "popularity": "5.51",
                "games": "3,691",
                "win_rate_diff": -0.77
            },
            "Ashe": {
                "Name": "Ashe",
                "win_rate": "48.90",
                "popularity": "5.10",
                "games": "3,419",
                "win_rate_diff": -1.1
            },
            "Smolder": {
                "Name": "Smolder",
                "win_rate": "49.97",
                "popularity": "5.06",
                "games": "3,390",
                "win_rate_diff": -0.03
            },
            "Lucian": {
                "Name": "Lucian",
                "win_rate": "51.27",
                "popularity": "4.77",
                "games": "3,197",
                "win_rate_diff": 1.27
            },
            "Yunara": {
                "Name": "Yunara",
                "win_rate": "53.24",
                "popularity": "4.30",
                "games": "2,883",
                "win_rate_diff": 3.24
            },
            "Tristana": {
                "Name": "Tristana",
                "win_rate": "49.76",
                "popularity": "3.68",
                "games": "2,464",
                "win_rate_diff": -0.24
            },
            "Vayne": {
                "Name": "Vayne",
                "win_rate": "47.59",
                "popularity": "3.63",
                "games": "2,429",
                "win_rate_diff": -2.41
            },
            "Aphelios": {
                "Name": "Aphelios",
                "win_rate": "50.95",
                "popularity": "3.47",
                "games": "2,326",
                "win_rate_diff": 0.95
            },
            "Sivir": {
                "Name": "Sivir",
                "win_rate": "51.82",
                "popularity": "2.79",
                "games": "1,868",
                "win_rate_diff": 1.82
            },
            "Draven": {
                "Name": "Draven",
                "win_rate": "49.44",
                "popularity": "2.67",
                "games": "1,786",
                "win_rate_diff": -0.56
            },
            "Twitch": {
                "Name": "Twitch",
                "win_rate": "49.63",
                "popularity": "2.20",
                "games": "1,473",
                "win_rate_diff": -0.37
            },
            "Xayah": {
                "Name": "Xayah",
                "win_rate": "51.02",
                "popularity": "1.98",
                "games": "1,329",
                "win_rate_diff": 1.02
            },
            "Zeri": {
                "Name": "Zeri",
                "win_rate": "55.78",
                "popularity": "1.96",
                "games": "1,316",
                "win_rate_diff": 5.78
            },
            "Varus": {
                "Name": "Varus",
                "win_rate": "54.95",
                "popularity": "1.90",
                "games": "1,272",
                "win_rate_diff": 4.95
            },
            "Samira": {
                "Name": "Samira",
                "win_rate": "50.24",
                "popularity": "1.90",
                "games": "1,272",
                "win_rate_diff": 0.24
            },
            "Ziggs": {
                "Name": "Ziggs",
                "win_rate": "50.57",
                "popularity": "1.17",
                "games": "787",
                "win_rate_diff": 0.57
            },
            "Mel": {
                "Name": "Mel",
                "win_rate": "56.43",
                "popularity": "1.04",
                "games": "700",
                "win_rate_diff": 6.43
            },
            "Corki": {
                "Name": "Corki",
                "win_rate": "55.76",
                "popularity": "0.91",
                "games": "608",
                "win_rate_diff": 5.76
            },
            "Kog'Maw": {
                "Name": "Kog'Maw",
                "win_rate": "51.13",
                "popularity": "0.86",
                "games": "573",
                "win_rate_diff": 1.13
            },
            "Nilah": {
                "Name": "Nilah",
                "win_rate": "50.19",
                "popularity": "0.78",
                "games": "520",
                "win_rate_diff": 0.19
            },
            "Kalista": {
                "Name": "Kalista",
                "win_rate": "55.77",
                "popularity": "0.71",
                "games": "477",
                "win_rate_diff": 5.77
            },
            "Swain": {
                "Name": "Swain",
                "win_rate": "51.02",
                "popularity": "0.59",
                "games": "394",
                "win_rate_diff": 1.02
            },
            "Yasuo": {
                "Name": "Yasuo",
                "win_rate": "50.54",
                "popularity": "0.55",
                "games": "370",
                "win_rate_diff": 0.54
            },
            "Lux": {
                "Name": "Lux",
                "win_rate": "51.43",
                "popularity": "0.31",
                "games": "210",
                "win_rate_diff": 1.43
            },
            "Veigar": {
                "Name": "Veigar",
                "win_rate": "53.65",
                "popularity": "0.29",
                "games": "192",
                "win_rate_diff": 3.65
            },
            "Hwei": {
                "Name": "Hwei",
                "win_rate": "50.53",
                "popularity": "0.28",
                "games": "190",
                "win_rate_diff": 0.53
            },
            "Brand": {
                "Name": "Brand",
                "win_rate": "48.42",
                "popularity": "0.28",
                "games": "190",
                "win_rate_diff": -1.58
            },
            "Seraphine": {
                "Name": "Seraphine",
                "win_rate": "51.09",
                "popularity": "0.27",
                "games": "184",
                "win_rate_diff": 1.09
            },
            "Karthus": {
                "Name": "Karthus",
                "win_rate": "52.90",
                "popularity": "0.23",
                "games": "155",
                "win_rate_diff": 2.9
            },
            "Senna": {
                "Name": "Senna",
                "win_rate": "62.02",
                "popularity": "0.19",
                "games": "129",
                "win_rate_diff": 12.02
            },
            "Syndra": {
                "Name": "Syndra",
                "win_rate": "57.63",
                "popularity": "0.18",
                "games": "118",
                "win_rate_diff": 7.63
            },
            "Vel'Koz": {
                "Name": "Vel'Koz",
                "win_rate": "50.88",
                "popularity": "0.17",
                "games": "114",
                "win_rate_diff": 0.88
            },
            "Aurelion Sol": {
                "Name": "Aurelion Sol",
                "win_rate": "50.00",
                "popularity": "0.16",
                "games": "110",
                "win_rate_diff": 0.0
            },
            "Cassiopeia": {
                "Name": "Cassiopeia",
                "win_rate": "43.84",
                "popularity": "0.11",
                "games": "73",
                "win_rate_diff": -6.16
            },
            "Viktor": {
                "Name": "Viktor",
                "win_rate": "45.71",
                "popularity": "0.10",
                "games": "70",
                "win_rate_diff": -4.29
            },
            "Xerath": {
                "Name": "Xerath",
                "win_rate": "52.24",
                "popularity": "0.10",
                "games": "67",
                "win_rate_diff": 2.24
            },
            "Katarina": {
                "Name": "Katarina",
                "win_rate": "60.42",
                "popularity": "0.07",
                "games": "48",
                "win_rate_diff": 10.42
            },
            "Malzahar": {
                "Name": "Malzahar",
                "win_rate": "47.83",
                "popularity": "0.07",
                "games": "46",
                "win_rate_diff": -2.17
            },
            "Zyra": {
                "Name": "Zyra",
                "win_rate": "52.78",
                "popularity": "0.05",
                "games": "36",
                "win_rate_diff": 2.78
            },
            "Heimerdinger": {
                "Name": "Heimerdinger",
                "win_rate": "48.48",
                "popularity": "0.05",
                "games": "33",
                "win_rate_diff": -1.52
            },
            "Akshan": {
                "Name": "Akshan",
                "win_rate": "53.13",
                "popularity": "0.05",
                "games": "32",
                "win_rate_diff": 3.13
            },
            "Anivia": {
                "Name": "Anivia",
                "win_rate": "60.71",
                "popularity": "0.04",
                "games": "28",
                "win_rate_diff": 10.71
            }
        },
        "support": {
            "Nami": {
                "Name": "Nami",
                "win_rate": "49.56",
                "popularity": "7.77",
                "games": "5,206",
                "win_rate_diff": -0.44
            },
            "Thresh": {
                "Name": "Thresh",
                "win_rate": "49.23",
                "popularity": "5.43",
                "games": "3,636",
                "win_rate_diff": -0.77
            },
            "Karma": {
                "Name": "Karma",
                "win_rate": "52.74",
                "popularity": "5.16",
                "games": "3,455",
                "win_rate_diff": 2.74
            },
            "Lulu": {
                "Name": "Lulu",
                "win_rate": "51.19",
                "popularity": "4.89",
                "games": "3,274",
                "win_rate_diff": 1.19
            },
            "Milio": {
                "Name": "Milio",
                "win_rate": "50.17",
                "popularity": "4.86",
                "games": "3,255",
                "win_rate_diff": 0.17
            },
            "Nautilus": {
                "Name": "Nautilus",
                "win_rate": "50.78",
                "popularity": "4.62",
                "games": "3,094",
                "win_rate_diff": 0.78
            },
            "Bard": {
                "Name": "Bard",
                "win_rate": "48.92",
                "popularity": "4.01",
                "games": "2,684",
                "win_rate_diff": -1.08
            },
            "Leona": {
                "Name": "Leona",
                "win_rate": "50.50",
                "popularity": "3.58",
                "games": "2,400",
                "win_rate_diff": 0.5
            },
            "Pyke": {
                "Name": "Pyke",
                "win_rate": "52.40",
                "popularity": "3.32",
                "games": "2,227",
                "win_rate_diff": 2.4
            },
            "Soraka": {
                "Name": "Soraka",
                "win_rate": "47.64",
                "popularity": "2.98",
                "games": "1,994",
                "win_rate_diff": -2.36
            },
            "Braum": {
                "Name": "Braum",
                "win_rate": "51.39",
                "popularity": "2.85",
                "games": "1,911",
                "win_rate_diff": 1.39
            },
            "Janna": {
                "Name": "Janna",
                "win_rate": "49.21",
                "popularity": "2.83",
                "games": "1,898",
                "win_rate_diff": -0.79
            },
            "Blitzcrank": {
                "Name": "Blitzcrank",
                "win_rate": "52.50",
                "popularity": "2.60",
                "games": "1,743",
                "win_rate_diff": 2.5
            },
            "Rakan": {
                "Name": "Rakan",
                "win_rate": "50.65",
                "popularity": "2.41",
                "games": "1,613",
                "win_rate_diff": 0.65
            },
            "Alistar": {
                "Name": "Alistar",
                "win_rate": "50.57",
                "popularity": "2.37",
                "games": "1,588",
                "win_rate_diff": 0.57
            },
            "Yuumi": {
                "Name": "Yuumi",
                "win_rate": "55.91",
                "popularity": "2.27",
                "games": "1,522",
                "win_rate_diff": 5.91
            },
            "Seraphine": {
                "Name": "Seraphine",
                "win_rate": "52.43",
                "popularity": "2.06",
                "games": "1,381",
                "win_rate_diff": 2.43
            },
            "Lux": {
                "Name": "Lux",
                "win_rate": "54.35",
                "popularity": "2.04",
                "games": "1,367",
                "win_rate_diff": 4.35
            },
            "Morgana": {
                "Name": "Morgana",
                "win_rate": "51.58",
                "popularity": "1.84",
                "games": "1,231",
                "win_rate_diff": 1.58
            },
            "Senna": {
                "Name": "Senna",
                "win_rate": "50.49",
                "popularity": "1.83",
                "games": "1,228",
                "win_rate_diff": 0.49
            },
            "Rell": {
                "Name": "Rell",
                "win_rate": "52.98",
                "popularity": "1.81",
                "games": "1,210",
                "win_rate_diff": 2.98
            },
            "Sona": {
                "Name": "Sona",
                "win_rate": "53.14",
                "popularity": "1.76",
                "games": "1,180",
                "win_rate_diff": 3.14
            },
            "Neeko": {
                "Name": "Neeko",
                "win_rate": "54.29",
                "popularity": "1.56",
                "games": "1,048",
                "win_rate_diff": 4.29
            },
            "Zilean": {
                "Name": "Zilean",
                "win_rate": "48.56",
                "popularity": "1.45",
                "games": "970",
                "win_rate_diff": -1.44
            },
            "Mel": {
                "Name": "Mel",
                "win_rate": "58.35",
                "popularity": "1.45",
                "games": "970",
                "win_rate_diff": 8.35
            },
            "Vel'Koz": {
                "Name": "Vel'Koz",
                "win_rate": "49.02",
                "popularity": "1.44",
                "games": "965",
                "win_rate_diff": -0.98
            },
            "Zyra": {
                "Name": "Zyra",
                "win_rate": "51.73",
                "popularity": "1.43",
                "games": "955",
                "win_rate_diff": 1.73
            },
            "Pantheon": {
                "Name": "Pantheon",
                "win_rate": "50.96",
                "popularity": "1.40",
                "games": "936",
                "win_rate_diff": 0.96
            },
            "Poppy": {
                "Name": "Poppy",
                "win_rate": "48.99",
                "popularity": "1.26",
                "games": "841",
                "win_rate_diff": -1.01
            },
            "Swain": {
                "Name": "Swain",
                "win_rate": "53.71",
                "popularity": "1.23",
                "games": "821",
                "win_rate_diff": 3.71
            },
            "Xerath": {
                "Name": "Xerath",
                "win_rate": "59.19",
                "popularity": "1.21",
                "games": "811",
                "win_rate_diff": 9.19
            },
            "Elise": {
                "Name": "Elise",
                "win_rate": "44.96",
                "popularity": "1.20",
                "games": "803",
                "win_rate_diff": -5.04
            },
            "Brand": {
                "Name": "Brand",
                "win_rate": "49.68",
                "popularity": "1.15",
                "games": "771",
                "win_rate_diff": -0.32
            },
            "Renata Glasc": {
                "Name": "Renata Glasc",
                "win_rate": "50.98",
                "popularity": "0.83",
                "games": "559",
                "win_rate_diff": 0.98
            },
            "Maokai": {
                "Name": "Maokai",
                "win_rate": "48.51",
                "popularity": "0.80",
                "games": "538",
                "win_rate_diff": -1.49
            },
            "Tahm Kench": {
                "Name": "Tahm Kench",
                "win_rate": "56.84",
                "popularity": "0.79",
                "games": "526",
                "win_rate_diff": 6.84
            },
            "Taric": {
                "Name": "Taric",
                "win_rate": "53.95",
                "popularity": "0.77",
                "games": "519",
                "win_rate_diff": 3.95
            },
            "Shaco": {
                "Name": "Shaco",
                "win_rate": "50.50",
                "popularity": "0.74",
                "games": "499",
                "win_rate_diff": 0.5
            },
            "Sylas": {
                "Name": "Sylas",
                "win_rate": "54.26",
                "popularity": "0.67",
                "games": "446",
                "win_rate_diff": 4.26
            },
            "Zoe": {
                "Name": "Zoe",
                "win_rate": "53.80",
                "popularity": "0.47",
                "games": "316",
                "win_rate_diff": 3.8
            },
            "Fiddlesticks": {
                "Name": "Fiddlesticks",
                "win_rate": "50.00",
                "popularity": "0.41",
                "games": "276",
                "win_rate_diff": 0.0
            },
            "LeBlanc": {
                "Name": "LeBlanc",
                "win_rate": "52.21",
                "popularity": "0.41",
                "games": "272",
                "win_rate_diff": 2.21
            },
            "Ashe": {
                "Name": "Ashe",
                "win_rate": "56.74",
                "popularity": "0.32",
                "games": "215",
                "win_rate_diff": 6.74
            },
            "Teemo": {
                "Name": "Teemo",
                "win_rate": "53.27",
                "popularity": "0.32",
                "games": "214",
                "win_rate_diff": 3.27
            },
            "Nidalee": {
                "Name": "Nidalee",
                "win_rate": "56.99",
                "popularity": "0.29",
                "games": "193",
                "win_rate_diff": 6.99
            },
            "Amumu": {
                "Name": "Amumu",
                "win_rate": "51.61",
                "popularity": "0.28",
                "games": "186",
                "win_rate_diff": 1.61
            },
            "Shen": {
                "Name": "Shen",
                "win_rate": "45.29",
                "popularity": "0.25",
                "games": "170",
                "win_rate_diff": -4.71
            }
        }
    },
    "synergy": {
        "top": {
            "Zaahen": {
                "Name": "Zaahen",
                "win_rate": "51.29",
                "delta_1": "0.13",
                "delta_2": "-0.93",
                "pick_rate": "6.53",
                "games": "4,375"
            },
            "Malphite": {
                "Name": "Malphite",
                "win_rate": "55.18",
                "delta_1": "3.11",
                "delta_2": "1.13",
                "pick_rate": "3.92",
                "games": "2,626"
            },
            "Aatrox": {
                "Name": "Aatrox",
                "win_rate": "52.21",
                "delta_1": "1.83",
                "delta_2": "1.53",
                "pick_rate": "3.64",
                "games": "2,442"
            },
            "Darius": {
                "Name": "Darius",
                "win_rate": "49.91",
                "delta_1": "-0.77",
                "delta_2": "-1.35",
                "pick_rate": "3.16",
                "games": "2,116"
            },
            "Garen": {
                "Name": "Garen",
                "win_rate": "51.34",
                "delta_1": "0.45",
                "delta_2": "-0.35",
                "pick_rate": "2.90",
                "games": "1,942"
            },
            "Ambessa": {
                "Name": "Ambessa",
                "win_rate": "51.37",
                "delta_1": "1.19",
                "delta_2": "1.09",
                "pick_rate": "2.88",
                "games": "1,933"
            },
            "Mordekaiser": {
                "Name": "Mordekaiser",
                "win_rate": "50.21",
                "delta_1": "-0.59",
                "delta_2": "-1.29",
                "pick_rate": "2.78",
                "games": "1,866"
            },
            "Jax": {
                "Name": "Jax",
                "win_rate": "49.75",
                "delta_1": "-0.95",
                "delta_2": "-1.55",
                "pick_rate": "2.71",
                "games": "1,817"
            },
            "Renekton": {
                "Name": "Renekton",
                "win_rate": "51.35",
                "delta_1": "0.99",
                "delta_2": "0.72",
                "pick_rate": "2.65",
                "games": "1,774"
            },
            "Sett": {
                "Name": "Sett",
                "win_rate": "51.15",
                "delta_1": "0.08",
                "delta_2": "-0.90",
                "pick_rate": "2.54",
                "games": "1,701"
            },
            "Sion": {
                "Name": "Sion",
                "win_rate": "52.56",
                "delta_1": "1.78",
                "delta_2": "1.09",
                "pick_rate": "2.39",
                "games": "1,602"
            },
            "Dr. Mundo": {
                "Name": "Dr. Mundo",
                "win_rate": "49.06",
                "delta_1": "-1.81",
                "delta_2": "-2.58",
                "pick_rate": "2.39",
                "games": "1,602"
            },
            "Riven": {
                "Name": "Riven",
                "win_rate": "52.87",
                "delta_1": "1.35",
                "delta_2": "-0.08",
                "pick_rate": "2.32",
                "games": "1,553"
            },
            "Gwen": {
                "Name": "Gwen",
                "win_rate": "48.69",
                "delta_1": "-2.14",
                "delta_2": "-2.88",
                "pick_rate": "2.22",
                "games": "1,487"
            },
            "Jayce": {
                "Name": "Jayce",
                "win_rate": "49.89",
                "delta_1": "-0.13",
                "delta_2": "-0.06",
                "pick_rate": "2.12",
                "games": "1,419"
            },
            "Fiora": {
                "Name": "Fiora",
                "win_rate": "50.21",
                "delta_1": "-0.76",
                "delta_2": "-1.64",
                "pick_rate": "2.10",
                "games": "1,410"
            },
            "Yone": {
                "Name": "Yone",
                "win_rate": "52.53",
                "delta_1": "2.73",
                "delta_2": "3.01",
                "pick_rate": "1.98",
                "games": "1,325"
            },
            "K'Sante": {
                "Name": "K'Sante",
                "win_rate": "51.45",
                "delta_1": "2.15",
                "delta_2": "2.94",
                "pick_rate": "1.95",
                "games": "1,306"
            },
            "Irelia": {
                "Name": "Irelia",
                "win_rate": "49.56",
                "delta_1": "-1.14",
                "delta_2": "-1.75",
                "pick_rate": "1.87",
                "games": "1,253"
            },
            "Kayle": {
                "Name": "Kayle",
                "win_rate": "52.69",
                "delta_1": "0.99",
                "delta_2": "-0.62",
                "pick_rate": "1.86",
                "games": "1,247"
            },
            "Ornn": {
                "Name": "Ornn",
                "win_rate": "51.80",
                "delta_1": "1.08",
                "delta_2": "0.44",
                "pick_rate": "1.82",
                "games": "1,220"
            },
            "Cho'Gath": {
                "Name": "Cho'Gath",
                "win_rate": "51.96",
                "delta_1": "1.12",
                "delta_2": "0.37",
                "pick_rate": "1.79",
                "games": "1,201"
            },
            "Shen": {
                "Name": "Shen",
                "win_rate": "52.25",
                "delta_1": "1.36",
                "delta_2": "0.56",
                "pick_rate": "1.79",
                "games": "1,198"
            },
            "Gangplank": {
                "Name": "Gangplank",
                "win_rate": "50.89",
                "delta_1": "0.31",
                "delta_2": "-0.19",
                "pick_rate": "1.68",
                "games": "1,124"
            },
            "Vladimir": {
                "Name": "Vladimir",
                "win_rate": "52.18",
                "delta_1": "1.46",
                "delta_2": "0.82",
                "pick_rate": "1.57",
                "games": "1,054"
            },
            "Teemo": {
                "Name": "Teemo",
                "win_rate": "52.24",
                "delta_1": "0.88",
                "delta_2": "-0.40",
                "pick_rate": "1.56",
                "games": "1,047"
            },
            "Camille": {
                "Name": "Camille",
                "win_rate": "52.20",
                "delta_1": "1.60",
                "delta_2": "1.09",
                "pick_rate": "1.53",
                "games": "1,023"
            },
            "Singed": {
                "Name": "Singed",
                "win_rate": "53.50",
                "delta_1": "1.54",
                "delta_2": "-0.32",
                "pick_rate": "1.49",
                "games": "1,000"
            },
            "Yasuo": {
                "Name": "Yasuo",
                "win_rate": "51.18",
                "delta_1": "0.98",
                "delta_2": "0.87",
                "pick_rate": "1.45",
                "games": "973"
            },
            "Gnar": {
                "Name": "Gnar",
                "win_rate": "49.38",
                "delta_1": "-1.18",
                "delta_2": "-1.65",
                "pick_rate": "1.44",
                "games": "968"
            },
            "Gragas": {
                "Name": "Gragas",
                "win_rate": "53.05",
                "delta_1": "2.43",
                "delta_2": "1.89",
                "pick_rate": "1.42",
                "games": "950"
            },
            "Urgot": {
                "Name": "Urgot",
                "win_rate": "53.52",
                "delta_1": "1.87",
                "delta_2": "0.30",
                "pick_rate": "1.40",
                "games": "938"
            },
            "Nasus": {
                "Name": "Nasus",
                "win_rate": "48.90",
                "delta_1": "-1.59",
                "delta_2": "-1.99",
                "pick_rate": "1.29",
                "games": "865"
            },
            "Rumble": {
                "Name": "Rumble",
                "win_rate": "52.58",
                "delta_1": "1.91",
                "delta_2": "1.33",
                "pick_rate": "1.27",
                "games": "854"
            },
            "Yorick": {
                "Name": "Yorick",
                "win_rate": "48.26",
                "delta_1": "-2.26",
                "delta_2": "-2.69",
                "pick_rate": "1.20",
                "games": "806"
            },
            "Volibear": {
                "Name": "Volibear",
                "win_rate": "47.67",
                "delta_1": "-2.52",
                "delta_2": "-2.61",
                "pick_rate": "1.15",
                "games": "772"
            },
            "Tryndamere": {
                "Name": "Tryndamere",
                "win_rate": "51.56",
                "delta_1": "1.29",
                "delta_2": "1.10",
                "pick_rate": "1.10",
                "games": "739"
            },
            "Kennen": {
                "Name": "Kennen",
                "win_rate": "52.80",
                "delta_1": "1.16",
                "delta_2": "-0.39",
                "pick_rate": "1.07",
                "games": "714"
            },
            "Pantheon": {
                "Name": "Pantheon",
                "win_rate": "51.60",
                "delta_1": "0.68",
                "delta_2": "-0.16",
                "pick_rate": "0.98",
                "games": "655"
            },
            "Illaoi": {
                "Name": "Illaoi",
                "win_rate": "52.93",
                "delta_1": "2.22",
                "delta_2": "1.59",
                "pick_rate": "0.92",
                "games": "614"
            },
            "Akali": {
                "Name": "Akali",
                "win_rate": "54.08",
                "delta_1": "3.57",
                "delta_2": "3.14",
                "pick_rate": "0.90",
                "games": "601"
            },
            "Olaf": {
                "Name": "Olaf",
                "win_rate": "55.63",
                "delta_1": "4.11",
                "delta_2": "2.68",
                "pick_rate": "0.89",
                "games": "595"
            },
            "Vayne": {
                "Name": "Vayne",
                "win_rate": "54.10",
                "delta_1": "2.84",
                "delta_2": "1.67",
                "pick_rate": "0.87",
                "games": "586"
            },
            "Kled": {
                "Name": "Kled",
                "win_rate": "52.86",
                "delta_1": "1.16",
                "delta_2": "-0.46",
                "pick_rate": "0.84",
                "games": "560"
            },
            "Quinn": {
                "Name": "Quinn",
                "win_rate": "50.10",
                "delta_1": "-1.98",
                "delta_2": "-3.95",
                "pick_rate": "0.76",
                "games": "509"
            },
            "Swain": {
                "Name": "Swain",
                "win_rate": "54.82",
                "delta_1": "3.07",
                "delta_2": "1.41",
                "pick_rate": "0.70",
                "games": "467"
            },
            "Warwick": {
                "Name": "Warwick",
                "win_rate": "53.35",
                "delta_1": "1.65",
                "delta_2": "0.04",
                "pick_rate": "0.62",
                "games": "418"
            }
        },
        "jungle": {},
        "middle": {
            "Ahri": {
                "Name": "Ahri",
                "win_rate": "53.28",
                "delta_1": "1.83",
                "delta_2": "0.47",
                "pick_rate": "4.71",
                "games": "3,159"
            },
            "Syndra": {
                "Name": "Syndra",
                "win_rate": "52.57",
                "delta_1": "1.59",
                "delta_2": "0.70",
                "pick_rate": "4.32",
                "games": "2,897"
            },
            "Viktor": {
                "Name": "Viktor",
                "win_rate": "51.80",
                "delta_1": "1.11",
                "delta_2": "0.51",
                "pick_rate": "4.18",
                "games": "2,803"
            },
            "Sylas": {
                "Name": "Sylas",
                "win_rate": "51.88",
                "delta_1": "1.29",
                "delta_2": "0.79",
                "pick_rate": "4.08",
                "games": "2,735"
            },
            "Katarina": {
                "Name": "Katarina",
                "win_rate": "51.49",
                "delta_1": "0.38",
                "delta_2": "-0.64",
                "pick_rate": "3.91",
                "games": "2,618"
            },
            "Mel": {
                "Name": "Mel",
                "win_rate": "48.58",
                "delta_1": "-0.92",
                "delta_2": "-0.33",
                "pick_rate": "3.85",
                "games": "2,577"
            },
            "Orianna": {
                "Name": "Orianna",
                "win_rate": "52.63",
                "delta_1": "2.39",
                "delta_2": "2.24",
                "pick_rate": "3.63",
                "games": "2,434"
            },
            "Akali": {
                "Name": "Akali",
                "win_rate": "51.41",
                "delta_1": "0.78",
                "delta_2": "0.24",
                "pick_rate": "3.40",
                "games": "2,276"
            },
            "Malzahar": {
                "Name": "Malzahar",
                "win_rate": "51.55",
                "delta_1": "0.53",
                "delta_2": "-0.39",
                "pick_rate": "3.12",
                "games": "2,093"
            },
            "Yasuo": {
                "Name": "Yasuo",
                "win_rate": "50.63",
                "delta_1": "0.18",
                "delta_2": "-0.18",
                "pick_rate": "2.71",
                "games": "1,819"
            },
            "LeBlanc": {
                "Name": "LeBlanc",
                "win_rate": "51.14",
                "delta_1": "0.55",
                "delta_2": "0.04",
                "pick_rate": "2.49",
                "games": "1,666"
            },
            "Zoe": {
                "Name": "Zoe",
                "win_rate": "53.94",
                "delta_1": "2.77",
                "delta_2": "1.70",
                "pick_rate": "2.29",
                "games": "1,535"
            },
            "Fizz": {
                "Name": "Fizz",
                "win_rate": "51.77",
                "delta_1": "0.56",
                "delta_2": "-0.56",
                "pick_rate": "2.20",
                "games": "1,472"
            },
            "Xerath": {
                "Name": "Xerath",
                "win_rate": "53.33",
                "delta_1": "2.01",
                "delta_2": "0.77",
                "pick_rate": "2.15",
                "games": "1,442"
            },
            "Zed": {
                "Name": "Zed",
                "win_rate": "51.19",
                "delta_1": "0.56",
                "delta_2": "0.03",
                "pick_rate": "2.13",
                "games": "1,430"
            },
            "Galio": {
                "Name": "Galio",
                "win_rate": "52.78",
                "delta_1": "2.38",
                "delta_2": "2.06",
                "pick_rate": "2.12",
                "games": "1,419"
            },
            "Twisted Fate": {
                "Name": "Twisted Fate",
                "win_rate": "51.87",
                "delta_1": "0.76",
                "delta_2": "-0.26",
                "pick_rate": "1.96",
                "games": "1,313"
            },
            "Hwei": {
                "Name": "Hwei",
                "win_rate": "54.53",
                "delta_1": "3.95",
                "delta_2": "3.46",
                "pick_rate": "1.96",
                "games": "1,313"
            },
            "Ekko": {
                "Name": "Ekko",
                "win_rate": "49.53",
                "delta_1": "-1.51",
                "delta_2": "-2.46",
                "pick_rate": "1.90",
                "games": "1,272"
            },
            "Diana": {
                "Name": "Diana",
                "win_rate": "51.20",
                "delta_1": "-0.23",
                "delta_2": "-1.58",
                "pick_rate": "1.87",
                "games": "1,250"
            },
            "Vladimir": {
                "Name": "Vladimir",
                "win_rate": "47.67",
                "delta_1": "-2.85",
                "delta_2": "-3.27",
                "pick_rate": "1.86",
                "games": "1,244"
            },
            "Ryze": {
                "Name": "Ryze",
                "win_rate": "49.68",
                "delta_1": "-0.38",
                "delta_2": "-0.36",
                "pick_rate": "1.85",
                "games": "1,242"
            },
            "Veigar": {
                "Name": "Veigar",
                "win_rate": "49.38",
                "delta_1": "-1.53",
                "delta_2": "-2.34",
                "pick_rate": "1.80",
                "games": "1,205"
            },
            "Kassadin": {
                "Name": "Kassadin",
                "win_rate": "52.09",
                "delta_1": "0.79",
                "delta_2": "-0.42",
                "pick_rate": "1.75",
                "games": "1,173"
            },
            "Anivia": {
                "Name": "Anivia",
                "win_rate": "51.49",
                "delta_1": "-0.15",
                "delta_2": "-1.71",
                "pick_rate": "1.70",
                "games": "1,138"
            },
            "Lux": {
                "Name": "Lux",
                "win_rate": "51.12",
                "delta_1": "0.35",
                "delta_2": "-0.33",
                "pick_rate": "1.66",
                "games": "1,115"
            },
            "Yone": {
                "Name": "Yone",
                "win_rate": "45.77",
                "delta_1": "-3.54",
                "delta_2": "-2.75",
                "pick_rate": "1.64",
                "games": "1,099"
            },
            "Aurora": {
                "Name": "Aurora",
                "win_rate": "53.74",
                "delta_1": "3.65",
                "delta_2": "3.64",
                "pick_rate": "1.57",
                "games": "1,055"
            },
            "Lissandra": {
                "Name": "Lissandra",
                "win_rate": "51.57",
                "delta_1": "0.68",
                "delta_2": "-0.13",
                "pick_rate": "1.57",
                "games": "1,051"
            },
            "Taliyah": {
                "Name": "Taliyah",
                "win_rate": "55.53",
                "delta_1": "4.89",
                "delta_2": "4.33",
                "pick_rate": "1.40",
                "games": "940"
            },
            "Vex": {
                "Name": "Vex",
                "win_rate": "52.32",
                "delta_1": "0.57",
                "delta_2": "-1.09",
                "pick_rate": "1.38",
                "games": "925"
            },
            "Azir": {
                "Name": "Azir",
                "win_rate": "47.06",
                "delta_1": "-1.40",
                "delta_2": "0.24",
                "pick_rate": "1.37",
                "games": "918"
            },
            "Akshan": {
                "Name": "Akshan",
                "win_rate": "50.81",
                "delta_1": "-0.23",
                "delta_2": "-1.18",
                "pick_rate": "1.29",
                "games": "864"
            },
            "Aurelion Sol": {
                "Name": "Aurelion Sol",
                "win_rate": "46.22",
                "delta_1": "-4.88",
                "delta_2": "-5.89",
                "pick_rate": "1.08",
                "games": "727"
            },
            "Morgana": {
                "Name": "Morgana",
                "win_rate": "56.25",
                "delta_1": "4.93",
                "delta_2": "3.69",
                "pick_rate": "1.03",
                "games": "688"
            },
            "Qiyana": {
                "Name": "Qiyana",
                "win_rate": "50.23",
                "delta_1": "-0.93",
                "delta_2": "-2.00",
                "pick_rate": "0.97",
                "games": "653"
            },
            "Kayle": {
                "Name": "Kayle",
                "win_rate": "48.91",
                "delta_1": "-2.63",
                "delta_2": "-4.07",
                "pick_rate": "0.96",
                "games": "642"
            },
            "Irelia": {
                "Name": "Irelia",
                "win_rate": "48.93",
                "delta_1": "-1.21",
                "delta_2": "-1.26",
                "pick_rate": "0.90",
                "games": "605"
            },
            "Cassiopeia": {
                "Name": "Cassiopeia",
                "win_rate": "54.33",
                "delta_1": "3.26",
                "delta_2": "2.28",
                "pick_rate": "0.88",
                "games": "589"
            },
            "Swain": {
                "Name": "Swain",
                "win_rate": "53.06",
                "delta_1": "0.90",
                "delta_2": "-1.16",
                "pick_rate": "0.85",
                "games": "571"
            },
            "Naafiri": {
                "Name": "Naafiri",
                "win_rate": "52.33",
                "delta_1": "0.41",
                "delta_2": "-1.42",
                "pick_rate": "0.80",
                "games": "537"
            },
            "Vel'Koz": {
                "Name": "Vel'Koz",
                "win_rate": "52.84",
                "delta_1": "1.10",
                "delta_2": "-0.56",
                "pick_rate": "0.76",
                "games": "511"
            },
            "Annie": {
                "Name": "Annie",
                "win_rate": "54.25",
                "delta_1": "3.17",
                "delta_2": "2.17",
                "pick_rate": "0.74",
                "games": "494"
            },
            "Talon": {
                "Name": "Talon",
                "win_rate": "51.16",
                "delta_1": "-0.42",
                "delta_2": "-1.90",
                "pick_rate": "0.71",
                "games": "475"
            },
            "Smolder": {
                "Name": "Smolder",
                "win_rate": "41.46",
                "delta_1": "-7.56",
                "delta_2": "-6.48",
                "pick_rate": "0.61",
                "games": "410"
            },
            "Ziggs": {
                "Name": "Ziggs",
                "win_rate": "53.03",
                "delta_1": "2.45",
                "delta_2": "1.95",
                "pick_rate": "0.52",
                "games": "347"
            },
            "Malphite": {
                "Name": "Malphite",
                "win_rate": "54.73",
                "delta_1": "2.86",
                "delta_2": "1.08",
                "pick_rate": "0.50",
                "games": "338"
            }
        },
        "bottom": {
            "Kai'Sa": {
                "Name": "Kai'Sa",
                "win_rate": "50.00",
                "delta_1": "-0.34",
                "delta_2": "-0.58",
                "pick_rate": "10.01",
                "games": "6,710"
            },
            "Miss Fortune": {
                "Name": "Miss Fortune",
                "win_rate": "54.32",
                "delta_1": "2.68",
                "delta_2": "1.13",
                "pick_rate": "9.42",
                "games": "6,313"
            },
            "Jhin": {
                "Name": "Jhin",
                "win_rate": "51.44",
                "delta_1": "0.56",
                "delta_2": "-0.22",
                "pick_rate": "7.71",
                "games": "5,165"
            },
            "Caitlyn": {
                "Name": "Caitlyn",
                "win_rate": "48.88",
                "delta_1": "-1.34",
                "delta_2": "-1.46",
                "pick_rate": "5.81",
                "games": "3,893"
            },
            "Ezreal": {
                "Name": "Ezreal",
                "win_rate": "49.52",
                "delta_1": "-0.40",
                "delta_2": "-0.24",
                "pick_rate": "5.73",
                "games": "3,837"
            },
            "Ashe": {
                "Name": "Ashe",
                "win_rate": "53.95",
                "delta_1": "2.62",
                "delta_2": "1.37",
                "pick_rate": "5.29",
                "games": "3,542"
            },
            "Jinx": {
                "Name": "Jinx",
                "win_rate": "51.47",
                "delta_1": "0.19",
                "delta_2": "-1.00",
                "pick_rate": "5.17",
                "games": "3,464"
            },
            "Smolder": {
                "Name": "Smolder",
                "win_rate": "52.03",
                "delta_1": "0.97",
                "delta_2": "-0.01",
                "pick_rate": "5.10",
                "games": "3,417"
            },
            "Lucian": {
                "Name": "Lucian",
                "win_rate": "51.42",
                "delta_1": "0.82",
                "delta_2": "0.31",
                "pick_rate": "4.63",
                "games": "3,102"
            },
            "Yunara": {
                "Name": "Yunara",
                "win_rate": "50.31",
                "delta_1": "0.86",
                "delta_2": "1.49",
                "pick_rate": "4.10",
                "games": "2,745"
            },
            "Vayne": {
                "Name": "Vayne",
                "win_rate": "51.58",
                "delta_1": "-0.06",
                "delta_2": "-1.61",
                "pick_rate": "3.72",
                "games": "2,495"
            },
            "Tristana": {
                "Name": "Tristana",
                "win_rate": "50.27",
                "delta_1": "-0.93",
                "delta_2": "-2.05",
                "pick_rate": "3.57",
                "games": "2,391"
            },
            "Aphelios": {
                "Name": "Aphelios",
                "win_rate": "51.48",
                "delta_1": "0.81",
                "delta_2": "0.22",
                "pick_rate": "3.32",
                "games": "2,224"
            },
            "Sivir": {
                "Name": "Sivir",
                "win_rate": "49.38",
                "delta_1": "-1.40",
                "delta_2": "-2.10",
                "pick_rate": "2.77",
                "games": "1,857"
            },
            "Draven": {
                "Name": "Draven",
                "win_rate": "51.14",
                "delta_1": "0.42",
                "delta_2": "-0.21",
                "pick_rate": "2.48",
                "games": "1,664"
            },
            "Twitch": {
                "Name": "Twitch",
                "win_rate": "49.97",
                "delta_1": "-0.80",
                "delta_2": "-1.47",
                "pick_rate": "2.26",
                "games": "1,515"
            },
            "Zeri": {
                "Name": "Zeri",
                "win_rate": "48.78",
                "delta_1": "-1.41",
                "delta_2": "-1.51",
                "pick_rate": "1.96",
                "games": "1,314"
            },
            "Xayah": {
                "Name": "Xayah",
                "win_rate": "51.53",
                "delta_1": "0.59",
                "delta_2": "-0.25",
                "pick_rate": "1.95",
                "games": "1,308"
            },
            "Varus": {
                "Name": "Varus",
                "win_rate": "50.59",
                "delta_1": "1.34",
                "delta_2": "2.18",
                "pick_rate": "1.91",
                "games": "1,279"
            },
            "Samira": {
                "Name": "Samira",
                "win_rate": "50.08",
                "delta_1": "-0.77",
                "delta_2": "-1.52",
                "pick_rate": "1.83",
                "games": "1,224"
            },
            "Ziggs": {
                "Name": "Ziggs",
                "win_rate": "54.07",
                "delta_1": "2.47",
                "delta_2": "0.95",
                "pick_rate": "1.37",
                "games": "921"
            },
            "Mel": {
                "Name": "Mel",
                "win_rate": "51.82",
                "delta_1": "1.35",
                "delta_2": "0.97",
                "pick_rate": "1.19",
                "games": "795"
            },
            "Corki": {
                "Name": "Corki",
                "win_rate": "51.83",
                "delta_1": "1.83",
                "delta_2": "1.93",
                "pick_rate": "0.90",
                "games": "602"
            },
            "Kog'Maw": {
                "Name": "Kog'Maw",
                "win_rate": "55.87",
                "delta_1": "4.17",
                "delta_2": "2.55",
                "pick_rate": "0.80",
                "games": "537"
            },
            "Swain": {
                "Name": "Swain",
                "win_rate": "53.62",
                "delta_1": "1.13",
                "delta_2": "-1.26",
                "pick_rate": "0.76",
                "games": "511"
            },
            "Nilah": {
                "Name": "Nilah",
                "win_rate": "50.84",
                "delta_1": "-1.04",
                "delta_2": "-2.83",
                "pick_rate": "0.71",
                "games": "476"
            },
            "Kalista": {
                "Name": "Kalista",
                "win_rate": "46.29",
                "delta_1": "-3.12",
                "delta_2": "-2.44",
                "pick_rate": "0.66",
                "games": "445"
            },
            "Yasuo": {
                "Name": "Yasuo",
                "win_rate": "59.19",
                "delta_1": "7.33",
                "delta_2": "5.56",
                "pick_rate": "0.48",
                "games": "321"
            },
            "Lux": {
                "Name": "Lux",
                "win_rate": "58.21",
                "delta_1": "5.97",
                "delta_2": "3.82",
                "pick_rate": "0.40",
                "games": "268"
            },
            "Brand": {
                "Name": "Brand",
                "win_rate": "57.31",
                "delta_1": "4.79",
                "delta_2": "2.36",
                "pick_rate": "0.38",
                "games": "253"
            },
            "Hwei": {
                "Name": "Hwei",
                "win_rate": "57.40",
                "delta_1": "5.80",
                "delta_2": "4.28",
                "pick_rate": "0.33",
                "games": "223"
            },
            "Veigar": {
                "Name": "Veigar",
                "win_rate": "49.77",
                "delta_1": "-2.01",
                "delta_2": "-3.69",
                "pick_rate": "0.32",
                "games": "213"
            },
            "Seraphine": {
                "Name": "Seraphine",
                "win_rate": "59.52",
                "delta_1": "8.61",
                "delta_2": "7.79",
                "pick_rate": "0.31",
                "games": "210"
            },
            "Karthus": {
                "Name": "Karthus",
                "win_rate": "55.76",
                "delta_1": "3.88",
                "delta_2": "2.09",
                "pick_rate": "0.25",
                "games": "165"
            },
            "Aurelion Sol": {
                "Name": "Aurelion Sol",
                "win_rate": "57.72",
                "delta_1": "5.97",
                "delta_2": "4.31",
                "pick_rate": "0.22",
                "games": "149"
            },
            "Vel'Koz": {
                "Name": "Vel'Koz",
                "win_rate": "54.93",
                "delta_1": "2.47",
                "delta_2": "0.11",
                "pick_rate": "0.21",
                "games": "142"
            },
            "Senna": {
                "Name": "Senna",
                "win_rate": "53.96",
                "delta_1": "3.35",
                "delta_2": "2.82",
                "pick_rate": "0.21",
                "games": "139"
            },
            "Syndra": {
                "Name": "Syndra",
                "win_rate": "51.82",
                "delta_1": "0.23",
                "delta_2": "-1.28",
                "pick_rate": "0.16",
                "games": "110"
            },
            "Cassiopeia": {
                "Name": "Cassiopeia",
                "win_rate": "52.17",
                "delta_1": "0.23",
                "delta_2": "-1.62",
                "pick_rate": "0.14",
                "games": "92"
            },
            "Xerath": {
                "Name": "Xerath",
                "win_rate": "49.25",
                "delta_1": "-1.46",
                "delta_2": "-2.08",
                "pick_rate": "0.10",
                "games": "67"
            },
            "Viktor": {
                "Name": "Viktor",
                "win_rate": "53.03",
                "delta_1": "1.70",
                "delta_2": "0.45",
                "pick_rate": "0.10",
                "games": "66"
            },
            "Zyra": {
                "Name": "Zyra",
                "win_rate": "44.44",
                "delta_1": "-7.98",
                "delta_2": "-10.29",
                "pick_rate": "0.08",
                "games": "54"
            },
            "Katarina": {
                "Name": "Katarina",
                "win_rate": "52.38",
                "delta_1": "0.61",
                "delta_2": "-1.07",
                "pick_rate": "0.06",
                "games": "42"
            },
            "Heimerdinger": {
                "Name": "Heimerdinger",
                "win_rate": "41.67",
                "delta_1": "-10.14",
                "delta_2": "-11.86",
                "pick_rate": "0.05",
                "games": "36"
            },
            "Malzahar": {
                "Name": "Malzahar",
                "win_rate": "48.39",
                "delta_1": "-2.65",
                "delta_2": "-3.60",
                "pick_rate": "0.05",
                "games": "31"
            },
            "Taliyah": {
                "Name": "Taliyah",
                "win_rate": "57.69",
                "delta_1": "6.58",
                "delta_2": "5.57",
                "pick_rate": "0.04",
                "games": "26"
            },
            "Irelia": {
                "Name": "Irelia",
                "win_rate": "58.33",
                "delta_1": "9.66",
                "delta_2": "11.08",
                "pick_rate": "0.04",
                "games": "24"
            }
        },
        "support": {
            "Nami": {
                "Name": "Nami",
                "win_rate": "52.10",
                "delta_1": "0.53",
                "delta_2": "-0.95",
                "pick_rate": "7.56",
                "games": "5,065"
            },
            "Thresh": {
                "Name": "Thresh",
                "win_rate": "51.73",
                "delta_1": "0.74",
                "delta_2": "-0.15",
                "pick_rate": "5.31",
                "games": "3,555"
            },
            "Karma": {
                "Name": "Karma",
                "win_rate": "52.04",
                "delta_1": "0.93",
                "delta_2": "-0.09",
                "pick_rate": "5.18",
                "games": "3,474"
            },
            "Lulu": {
                "Name": "Lulu",
                "win_rate": "50.94",
                "delta_1": "0.34",
                "delta_2": "-0.16",
                "pick_rate": "5.09",
                "games": "3,408"
            },
            "Milio": {
                "Name": "Milio",
                "win_rate": "51.53",
                "delta_1": "0.05",
                "delta_2": "-1.35",
                "pick_rate": "4.82",
                "games": "3,229"
            },
            "Nautilus": {
                "Name": "Nautilus",
                "win_rate": "49.59",
                "delta_1": "-0.82",
                "delta_2": "-1.14",
                "pick_rate": "4.40",
                "games": "2,950"
            },
            "Bard": {
                "Name": "Bard",
                "win_rate": "52.56",
                "delta_1": "1.26",
                "delta_2": "0.04",
                "pick_rate": "3.91",
                "games": "2,620"
            },
            "Leona": {
                "Name": "Leona",
                "win_rate": "52.58",
                "delta_1": "1.29",
                "delta_2": "0.08",
                "pick_rate": "3.50",
                "games": "2,343"
            },
            "Braum": {
                "Name": "Braum",
                "win_rate": "52.62",
                "delta_1": "1.51",
                "delta_2": "0.50",
                "pick_rate": "3.30",
                "games": "2,214"
            },
            "Pyke": {
                "Name": "Pyke",
                "win_rate": "51.61",
                "delta_1": "0.94",
                "delta_2": "0.36",
                "pick_rate": "3.20",
                "games": "2,147"
            },
            "Janna": {
                "Name": "Janna",
                "win_rate": "54.46",
                "delta_1": "2.78",
                "delta_2": "1.18",
                "pick_rate": "2.94",
                "games": "1,972"
            },
            "Soraka": {
                "Name": "Soraka",
                "win_rate": "50.65",
                "delta_1": "-0.73",
                "delta_2": "-2.02",
                "pick_rate": "2.86",
                "games": "1,919"
            },
            "Blitzcrank": {
                "Name": "Blitzcrank",
                "win_rate": "51.67",
                "delta_1": "0.91",
                "delta_2": "0.25",
                "pick_rate": "2.73",
                "games": "1,827"
            },
            "Yuumi": {
                "Name": "Yuumi",
                "win_rate": "49.86",
                "delta_1": "0.84",
                "delta_2": "1.92",
                "pick_rate": "2.58",
                "games": "1,731"
            },
            "Rakan": {
                "Name": "Rakan",
                "win_rate": "53.18",
                "delta_1": "2.53",
                "delta_2": "1.97",
                "pick_rate": "2.39",
                "games": "1,602"
            },
            "Alistar": {
                "Name": "Alistar",
                "win_rate": "51.05",
                "delta_1": "0.89",
                "delta_2": "0.83",
                "pick_rate": "2.34",
                "games": "1,567"
            },
            "Lux": {
                "Name": "Lux",
                "win_rate": "47.38",
                "delta_1": "-2.63",
                "delta_2": "-2.54",
                "pick_rate": "2.08",
                "games": "1,391"
            },
            "Seraphine": {
                "Name": "Seraphine",
                "win_rate": "54.78",
                "delta_1": "3.86",
                "delta_2": "3.03",
                "pick_rate": "2.01",
                "games": "1,349"
            },
            "Morgana": {
                "Name": "Morgana",
                "win_rate": "50.16",
                "delta_1": "-0.61",
                "delta_2": "-1.28",
                "pick_rate": "1.87",
                "games": "1,256"
            },
            "Senna": {
                "Name": "Senna",
                "win_rate": "50.53",
                "delta_1": "-0.19",
                "delta_2": "-0.81",
                "pick_rate": "1.82",
                "games": "1,221"
            },
            "Sona": {
                "Name": "Sona",
                "win_rate": "56.00",
                "delta_1": "4.35",
                "delta_2": "2.79",
                "pick_rate": "1.77",
                "games": "1,184"
            },
            "Rell": {
                "Name": "Rell",
                "win_rate": "52.32",
                "delta_1": "1.73",
                "delta_2": "1.23",
                "pick_rate": "1.73",
                "games": "1,162"
            },
            "Neeko": {
                "Name": "Neeko",
                "win_rate": "49.62",
                "delta_1": "-0.69",
                "delta_2": "-0.90",
                "pick_rate": "1.59",
                "games": "1,066"
            },
            "Zilean": {
                "Name": "Zilean",
                "win_rate": "54.36",
                "delta_1": "2.88",
                "delta_2": "1.48",
                "pick_rate": "1.58",
                "games": "1,056"
            },
            "Mel": {
                "Name": "Mel",
                "win_rate": "46.65",
                "delta_1": "-1.81",
                "delta_2": "-0.16",
                "pick_rate": "1.52",
                "games": "1,016"
            },
            "Zyra": {
                "Name": "Zyra",
                "win_rate": "51.12",
                "delta_1": "0.07",
                "delta_2": "-0.88",
                "pick_rate": "1.46",
                "games": "980"
            },
            "Pantheon": {
                "Name": "Pantheon",
                "win_rate": "50.00",
                "delta_1": "-0.59",
                "delta_2": "-1.10",
                "pick_rate": "1.39",
                "games": "932"
            },
            "Vel'Koz": {
                "Name": "Vel'Koz",
                "win_rate": "51.56",
                "delta_1": "0.25",
                "delta_2": "-0.98",
                "pick_rate": "1.34",
                "games": "900"
            },
            "Poppy": {
                "Name": "Poppy",
                "win_rate": "51.66",
                "delta_1": "0.31",
                "delta_2": "-0.94",
                "pick_rate": "1.26",
                "games": "844"
            },
            "Elise": {
                "Name": "Elise",
                "win_rate": "55.90",
                "delta_1": "4.00",
                "delta_2": "2.20",
                "pick_rate": "1.25",
                "games": "839"
            },
            "Xerath": {
                "Name": "Xerath",
                "win_rate": "50.89",
                "delta_1": "0.70",
                "delta_2": "0.61",
                "pick_rate": "1.17",
                "games": "786"
            },
            "Brand": {
                "Name": "Brand",
                "win_rate": "53.01",
                "delta_1": "1.73",
                "delta_2": "0.53",
                "pick_rate": "1.17",
                "games": "781"
            },
            "Swain": {
                "Name": "Swain",
                "win_rate": "49.10",
                "delta_1": "-1.39",
                "delta_2": "-1.79",
                "pick_rate": "1.16",
                "games": "780"
            },
            "Tahm Kench": {
                "Name": "Tahm Kench",
                "win_rate": "49.38",
                "delta_1": "-0.95",
                "delta_2": "-1.20",
                "pick_rate": "0.84",
                "games": "565"
            },
            "Maokai": {
                "Name": "Maokai",
                "win_rate": "53.74",
                "delta_1": "2.16",
                "delta_2": "0.67",
                "pick_rate": "0.78",
                "games": "521"
            },
            "Renata Glasc": {
                "Name": "Renata Glasc",
                "win_rate": "49.10",
                "delta_1": "-1.42",
                "delta_2": "-1.85",
                "pick_rate": "0.75",
                "games": "501"
            },
            "Taric": {
                "Name": "Taric",
                "win_rate": "53.28",
                "delta_1": "1.36",
                "delta_2": "-0.46",
                "pick_rate": "0.73",
                "games": "488"
            },
            "Sylas": {
                "Name": "Sylas",
                "win_rate": "50.22",
                "delta_1": "-0.16",
                "delta_2": "-0.44",
                "pick_rate": "0.67",
                "games": "446"
            },
            "Shaco": {
                "Name": "Shaco",
                "win_rate": "52.36",
                "delta_1": "1.30",
                "delta_2": "0.33",
                "pick_rate": "0.66",
                "games": "445"
            },
            "Zoe": {
                "Name": "Zoe",
                "win_rate": "53.49",
                "delta_1": "3.51",
                "delta_2": "3.61",
                "pick_rate": "0.51",
                "games": "344"
            },
            "LeBlanc": {
                "Name": "LeBlanc",
                "win_rate": "46.82",
                "delta_1": "-3.66",
                "delta_2": "-4.05",
                "pick_rate": "0.40",
                "games": "267"
            },
            "Fiddlesticks": {
                "Name": "Fiddlesticks",
                "win_rate": "51.44",
                "delta_1": "-0.10",
                "delta_2": "-1.55",
                "pick_rate": "0.36",
                "games": "243"
            },
            "Ashe": {
                "Name": "Ashe",
                "win_rate": "46.60",
                "delta_1": "-1.42",
                "delta_2": "0.66",
                "pick_rate": "0.31",
                "games": "206"
            },
            "Nidalee": {
                "Name": "Nidalee",
                "win_rate": "55.78",
                "delta_1": "4.69",
                "delta_2": "3.69",
                "pick_rate": "0.30",
                "games": "199"
            },
            "Amumu": {
                "Name": "Amumu",
                "win_rate": "52.53",
                "delta_1": "0.72",
                "delta_2": "-1.01",
                "pick_rate": "0.30",
                "games": "198"
            },
            "Teemo": {
                "Name": "Teemo",
                "win_rate": "54.87",
                "delta_1": "3.89",
                "delta_2": "2.99",
                "pick_rate": "0.29",
                "games": "195"
            },
            "Galio": {
                "Name": "Galio",
                "win_rate": "51.88",
                "delta_1": "1.18",
                "delta_2": "0.57",
                "pick_rate": "0.24",
                "games": "160"
            }
        }
    }
}